agentlys_tools/__init__.py
agentlys_tools/code_editor/__init__.py
agentlys_tools/code_editor/code_editor.py
agentlys_tools/code_editor/code_editor_utils.py
agentlys_tools/code_editor/directory_utils.py
agentlys_tools/code_editor/tests/test_auto_linting.py
agentlys_tools/code_editor/tests/test_code_editor.py
agentlys_tools/code_editor/tests/test_directory_utils.py
agentlys_tools/code_editor/tests/test_edit_file.py
agentlys_tools/code_editor/tests/test_search_files.py
agentlys_tools/terminal/__init__.py
agentlys_tools/terminal/terminal.py
agentlys_tools/terminal/tests/test_terminal.py
agentlys_tools-0.2.0.dist-info/METADATA
agentlys_tools-0.2.0.dist-info/WHEEL
agentlys_tools-0.2.0.dist-info/entry_points.txt
agentlys_tools-0.2.0.dist-info/top_level.txt
agentlys_tools-0.2.0.dist-info/RECORD
