Metadata-Version: 2.4
Name: agentlys_tools
Version: 0.2.0
Summary: Shared tools for Agentlys
Author-email: Benjamin Derville <benjamin@myriade.ai>
Project-URL: Repository, https://github.com/myriade-ai/agentlys-tools
Project-URL: Changelog, https://github.com/myriade-ai/agentlys-tools/blob/master/CHANGELOG.md
Requires-Python: >=3.9
Provides-Extra: code-editor
Requires-Dist: pillow>=11.3.0; extra == "code-editor"
Requires-Dist: ruff>=0.13.0; extra == "code-editor"
Provides-Extra: terminal
Provides-Extra: all
Requires-Dist: agentlys_tools[code_editor,terminal]; extra == "all"
